marketo/__init__.py
marketo/auth.py
marketo/exceptions.py
marketo/rfc3339.py
marketo/run_me.py
marketo/version.py
marketo/wrapper/__init__.py
marketo/wrapper/get_lead.py
marketo/wrapper/get_lead_activity.py
marketo/wrapper/get_lead_changes.py
marketo/wrapper/get_multiple_leads.py
marketo/wrapper/lead_activity.py
marketo/wrapper/lead_record.py
marketo/wrapper/request_campaign.py
marketo/wrapper/sync_lead.py
marketo_tronok-0.2.5.dist-info/METADATA
marketo_tronok-0.2.5.dist-info/WHEEL
marketo_tronok-0.2.5.dist-info/top_level.txt
marketo_tronok-0.2.5.dist-info/RECORD
