Metadata-Version: 2.1
Name: marketo-tronok
Version: 0.2.5
Summary: marketo-python is a python query client that wraps the Marketo SOAP API.
Home-page: https://github.com/tronok/marketo-python
Author: Dmitry Kalashnikov
Author-email: kalashnikovdm@gmail.com
License: MIT License
Platform: UNKNOWN
Requires-Dist: requests
Requires-Dist: iso8601
